nirvar/__init__.py
nirvar/data/__init__.py
nirvar/data/clean_stocks.py
nirvar/features/__init__.py
nirvar/features/build_features.py
nirvar/models/__init__.py
nirvar/models/generativeVAR.py
nirvar/models/predict_model.py
nirvar/models/train_model.py
nirvar/visualization/0.3-ARI-comparisons.py
nirvar/visualization/0.3-SICCD-bars-plot.py
nirvar/visualization/0.3-embedding-dim.py
nirvar/visualization/0.3-turnover.py
nirvar/visualization/0.3-visualise-backtesting.py
nirvar/visualization/__init__.py
nirvar/visualization/factors_over_time.py
nirvar/visualization/utility_funcs.py
src/__init__.py
src/data/__init__.py
src/data/clean_stocks.py
src/features/__init__.py
src/features/build_features.py
src/models/__init__.py
src/models/generativeVAR.py
src/models/predict_model.py
src/models/train_model.py
src/visualization/0.3-ARI-comparisons.py
src/visualization/0.3-SICCD-bars-plot.py
src/visualization/0.3-embedding-dim.py
src/visualization/0.3-turnover.py
src/visualization/0.3-visualise-backtesting.py
src/visualization/__init__.py
src/visualization/factors_over_time.py
src/visualization/utility_funcs.py
nirvar-1.1.0.dist-info/LICENSE
nirvar-1.1.0.dist-info/METADATA
nirvar-1.1.0.dist-info/WHEEL
nirvar-1.1.0.dist-info/top_level.txt
nirvar-1.1.0.dist-info/RECORD
