Metadata-Version: 2.1
Name: nirvar
Version: 1.1.0
Summary: Network Informed Restricted Vector Autoregression
Author: Brendan Martin
License: MIT
License-File: LICENSE
